odoo/addons/l10n_lu_intrastat_product/README.rst
odoo/addons/l10n_lu_intrastat_product/__init__.py
odoo/addons/l10n_lu_intrastat_product/__manifest__.py
odoo/addons/l10n_lu_intrastat_product/i18n/l10n_lu_intrastat_product.pot
odoo/addons/l10n_lu_intrastat_product/models/__init__.py
odoo/addons/l10n_lu_intrastat_product/models/intrastat_product_declaration.py
odoo/addons/l10n_lu_intrastat_product/readme/CONTRIBUTORS.rst
odoo/addons/l10n_lu_intrastat_product/readme/DESCRIPTION.rst
odoo/addons/l10n_lu_intrastat_product/report/__init__.py
odoo/addons/l10n_lu_intrastat_product/report/report_intrastat_product_product_declaration_xls.py
odoo/addons/l10n_lu_intrastat_product/static/description/icon.png
odoo/addons/l10n_lu_intrastat_product/static/description/index.html
odoo/addons/l10n_lu_intrastat_product/tests/__init__.py
odoo/addons/l10n_lu_intrastat_product/tests/test_intrastat_product.py
odoo14_addon_l10n_lu_intrastat_product-14.0.1.0.1.dist-info/METADATA
odoo14_addon_l10n_lu_intrastat_product-14.0.1.0.1.dist-info/WHEEL
odoo14_addon_l10n_lu_intrastat_product-14.0.1.0.1.dist-info/top_level.txt
odoo14_addon_l10n_lu_intrastat_product-14.0.1.0.1.dist-info/RECORD
